sphinx_algolia_crawler/__init__.py
sphinx_algolia_crawler/sphinx_algolia_crawler.py
sphinx_algolia_crawler-1.0.6.dist-info/LICENSE
sphinx_algolia_crawler-1.0.6.dist-info/METADATA
sphinx_algolia_crawler-1.0.6.dist-info/WHEEL
sphinx_algolia_crawler-1.0.6.dist-info/RECORD
