Metadata-Version: 2.1
Name: sphinx_algolia_crawler
Version: 1.0.6
Summary: This Sphinx extension uses Algolia's v1 Crawler API - and may even be run standalone via CLI (without Sphinx).
License: MIT
Author: Xsolla Backend
Author-email: xbe@xsolla.com
Requires-Python: >=3.10
Classifier: Framework :: Sphinx :: Extension
Classifier: Intended Audience :: Developers
Classifier: License :: OSI Approved :: MIT License
Classifier: Operating System :: OS Independent
Classifier: Programming Language :: Python :: 3
Classifier: Programming Language :: Python :: 3.10
Classifier: Programming Language :: Python :: 3.11
Classifier: Programming Language :: Python :: 3.12
Classifier: Programming Language :: Python :: 3.13
Classifier: Topic :: Internet :: WWW/HTTP :: Indexing/Search
Classifier: Topic :: Software Development :: Build Tools
Classifier: Topic :: Software Development :: Documentation
Requires-Dist: requests (>=2.32.3)
Requires-Dist: sphinx (>=7.3.7)
Project-URL: Homepage, https://github.com/Unidocs1/sphinx_algolia_crawler
Project-URL: Issues, https://github.com/Unidocs1/sphinx_algolia_crawler/issues
